metabypassrecaptcha3/__init__.py
metabypassrecaptcha3/main.py
metabypassrecaptcha3-0.0.1.dist-info/METADATA
metabypassrecaptcha3-0.0.1.dist-info/WHEEL
metabypassrecaptcha3-0.0.1.dist-info/RECORD
